{
    "nodes": [
        {
            "id": 0,
            "label": "LT"
        },
        {
            "id": 1,
            "label": "LT"
        },
        {
            "id": 2,
            "label": "ADD"
        },
        {
            "id": 3,
            "label": "LT"
        },
        {
            "id": 4,
            "label": "READ"
        },
        {
            "id": 5,
            "label": "ADD"
        },
        {
            "id": 6,
            "label": "LT"
        },
        {
            "id": 7,
            "label": "EQ"
        },
        {
            "id": 8,
            "label": "INIT"
        },
        {
            "id": 9,
            "label": "INIT"
        },
        {
            "id": 10,
            "label": "MUL"
        },
        {
            "id": 11,
            "label": "INIT"
        },
        {
            "id": 12,
            "label": "LT"
        },
        {
            "id": 13,
            "label": "LT"
        },
        {
            "id": 14,
            "label": "LT"
        },
        {
            "id": 15,
            "label": "LT"
        },
        {
            "id": 16,
            "label": "DIV"
        },
        {
            "id": 17,
            "label": "INIT"
        },
        {
            "id": 18,
            "label": "LT"
        },
        {
            "id": 19,
            "label": "INIT"
        },
        {
            "id": 20,
            "label": "READ"
        },
        {
            "id": 21,
            "label": "READ"
        },
        {
            "id": 22,
            "label": "READ"
        },
        {
            "id": 23,
            "label": "ADD"
        },
        {
            "id": 24,
            "label": "MUL"
        },
        {
            "id": 25,
            "label": "READ"
        },
        {
            "id": 26,
            "label": "LT"
        },
        {
            "id": 27,
            "label": "WRITE"
        },
        {
            "id": 28,
            "label": "LT"
        },
        {
            "id": 29,
            "label": "LT"
        },
        {
            "id": 30,
            "label": "MUL"
        },
        {
            "id": 31,
            "label": "LT"
        },
        {
            "id": 32,
            "label": "INIT"
        },
        {
            "id": 33,
            "label": "INIT"
        },
        {
            "id": 34,
            "label": "READ"
        },
        {
            "id": 35,
            "label": "WRITE"
        },
        {
            "id": 36,
            "label": "ADD"
        },
        {
            "id": 37,
            "label": "SUB"
        },
        {
            "id": 38,
            "label": "MUL"
        },
        {
            "id": 39,
            "label": "DIV"
        },
        {
            "id": 40,
            "label": "CONST"
        },
        {
            "id": 41,
            "label": "GT"
        },
        {
            "id": 42,
            "label": "LT"
        },
        {
            "id": 43,
            "label": "EQ"
        },
        {
            "id": 44,
            "label": "ASSIGN"
        },
        {
            "id": 45,
            "label": "READ"
        },
        {
            "id": 46,
            "label": "READ"
        },
        {
            "id": 47,
            "label": "CONST"
        },
        {
            "id": 48,
            "label": "LT"
        },
        {
            "id": 49,
            "label": "LT"
        },
        {
            "id": 50,
            "label": "LT"
        },
        {
            "id": 51,
            "label": "LT"
        },
        {
            "id": 52,
            "label": "LT"
        },
        {
            "id": 53,
            "label": "LT"
        },
        {
            "id": 54,
            "label": "MUL"
        },
        {
            "id": 55,
            "label": "LT"
        },
        {
            "id": 56,
            "label": "INIT"
        },
        {
            "id": 57,
            "label": "INIT"
        },
        {
            "id": 58,
            "label": "MUL"
        },
        {
            "id": 59,
            "label": "INIT"
        },
        {
            "id": 60,
            "label": "INIT"
        },
        {
            "id": 61,
            "label": "LT"
        },
        {
            "id": 62,
            "label": "MUL"
        },
        {
            "id": 63,
            "label": "MUL"
        },
        {
            "id": 64,
            "label": "DIV"
        },
        {
            "id": 65,
            "label": "LT"
        },
        {
            "id": 66,
            "label": "INIT"
        },
        {
            "id": 67,
            "label": "LT"
        },
        {
            "id": 68,
            "label": "ASSIGN"
        },
        {
            "id": 69,
            "label": "ASSIGN"
        },
        {
            "id": 70,
            "label": "READ"
        },
        {
            "id": 71,
            "label": "ADD"
        },
        {
            "id": 72,
            "label": "SUB"
        },
        {
            "id": 73,
            "label": "MUL"
        },
        {
            "id": 74,
            "label": "DIV"
        },
        {
            "id": 75,
            "label": "GT"
        },
        {
            "id": 76,
            "label": "LT"
        },
        {
            "id": 77,
            "label": "EQ"
        },
        {
            "id": 78,
            "label": "CONST"
        },
        {
            "id": 79,
            "label": "WRITE"
        },
        {
            "id": 80,
            "label": "AVG_N"
        },
        {
            "id": 81,
            "label": "INIT"
        },
        {
            "id": 82,
            "label": "ASSIGN"
        },
        {
            "id": 83,
            "label": "LT"
        },
        {
            "id": 84,
            "label": "LT"
        },
        {
            "id": 85,
            "label": "LT"
        },
        {
            "id": 86,
            "label": "LT"
        },
        {
            "id": 87,
            "label": "LT"
        },
        {
            "id": 88,
            "label": "READ"
        },
        {
            "id": 89,
            "label": "AVG_N"
        },
        {
            "id": 90,
            "label": "ADD"
        },
        {
            "id": 91,
            "label": "LT"
        },
        {
            "id": 92,
            "label": "LT"
        },
        {
            "id": 93,
            "label": "LT"
        },
        {
            "id": 94,
            "label": "INIT"
        },
        {
            "id": 95,
            "label": "DIV"
        },
        {
            "id": 96,
            "label": "LT"
        },
        {
            "id": 97,
            "label": "WRITE"
        },
        {
            "id": 98,
            "label": "ASSIGN"
        },
        {
            "id": 99,
            "label": "INIT"
        },
        {
            "id": 100,
            "label": "INIT"
        },
        {
            "id": 101,
            "label": "CONST"
        },
        {
            "id": 102,
            "label": "INIT"
        },
        {
            "id": 103,
            "label": "ASSIGN"
        },
        {
            "id": 104,
            "label": "ASSIGN"
        },
        {
            "id": 105,
            "label": "INIT"
        },
        {
            "id": 106,
            "label": "CONST"
        },
        {
            "id": 107,
            "label": "READ"
        },
        {
            "id": 108,
            "label": "CONST"
        },
        {
            "id": 109,
            "label": "ADD"
        },
        {
            "id": 110,
            "label": "CONST"
        },
        {
            "id": 111,
            "label": "SUB"
        },
        {
            "id": 112,
            "label": "CONST"
        },
        {
            "id": 113,
            "label": "MUL"
        },
        {
            "id": 114,
            "label": "CONST"
        },
        {
            "id": 115,
            "label": "DIV"
        },
        {
            "id": 116,
            "label": "CONST"
        },
        {
            "id": 117,
            "label": "GT"
        },
        {
            "id": 118,
            "label": "CONST"
        },
        {
            "id": 119,
            "label": "LT"
        },
        {
            "id": 120,
            "label": "CONST"
        },
        {
            "id": 121,
            "label": "EQ"
        },
        {
            "id": 122,
            "label": "CONST"
        },
        {
            "id": 123,
            "label": "CONST"
        },
        {
            "id": 124,
            "label": "CONST"
        },
        {
            "id": 125,
            "label": "CONST"
        },
        {
            "id": 126,
            "label": "WRITE"
        },
        {
            "id": 127,
            "label": "ASSIGN"
        },
        {
            "id": 128,
            "label": "CONST"
        },
        {
            "id": 129,
            "label": "EQ"
        },
        {
            "id": 130,
            "label": "ADD"
        },
        {
            "id": 131,
            "label": "LT"
        },
        {
            "id": 132,
            "label": "LT"
        },
        {
            "id": 133,
            "label": "CONST"
        },
        {
            "id": 134,
            "label": "LT"
        },
        {
            "id": 135,
            "label": "READ"
        },
        {
            "id": 136,
            "label": "INIT"
        },
        {
            "id": 137,
            "label": "INIT"
        },
        {
            "id": 138,
            "label": "CONST"
        },
        {
            "id": 139,
            "label": "ASSIGN"
        },
        {
            "id": 140,
            "label": "ASSIGN"
        },
        {
            "id": 141,
            "label": "INIT"
        },
        {
            "id": 142,
            "label": "CONST"
        },
        {
            "id": 143,
            "label": "INIT"
        },
        {
            "id": 144,
            "label": "READ"
        },
        {
            "id": 145,
            "label": "CONST"
        },
        {
            "id": 146,
            "label": "WRITE"
        },
        {
            "id": 147,
            "label": "CONST"
        },
        {
            "id": 148,
            "label": "ADD"
        },
        {
            "id": 149,
            "label": "CONST"
        },
        {
            "id": 150,
            "label": "SUB"
        },
        {
            "id": 151,
            "label": "CONST"
        },
        {
            "id": 152,
            "label": "MUL"
        },
        {
            "id": 153,
            "label": "CONST"
        },
        {
            "id": 154,
            "label": "DIV"
        },
        {
            "id": 155,
            "label": "CONST"
        },
        {
            "id": 156,
            "label": "GT"
        },
        {
            "id": 157,
            "label": "CONST"
        },
        {
            "id": 158,
            "label": "LT"
        },
        {
            "id": 159,
            "label": "CONST"
        },
        {
            "id": 160,
            "label": "EQ"
        },
        {
            "id": 161,
            "label": "CONST"
        },
        {
            "id": 162,
            "label": "CONST"
        },
        {
            "id": 163,
            "label": "CONST"
        },
        {
            "id": 164,
            "label": "CONST"
        },
        {
            "id": 165,
            "label": "CONST"
        },
        {
            "id": 166,
            "label": "CONST"
        },
        {
            "id": 167,
            "label": "CONST"
        },
        {
            "id": 168,
            "label": "LT"
        },
        {
            "id": 169,
            "label": "INIT"
        },
        {
            "id": 170,
            "label": "LT"
        },
        {
            "id": 171,
            "label": "LT"
        },
        {
            "id": 172,
            "label": "LT"
        },
        {
            "id": 173,
            "label": "CONST"
        },
        {
            "id": 174,
            "label": "CONST"
        },
        {
            "id": 175,
            "label": "CONST"
        },
        {
            "id": 176,
            "label": "INIT"
        },
        {
            "id": 177,
            "label": "INIT"
        },
        {
            "id": 178,
            "label": "LT"
        },
        {
            "id": 179,
            "label": "LT"
        },
        {
            "id": 180,
            "label": "INIT"
        },
        {
            "id": 181,
            "label": "LT"
        },
        {
            "id": 182,
            "label": "LT"
        },
        {
            "id": 183,
            "label": "DIV"
        },
        {
            "id": 184,
            "label": "LT"
        },
        {
            "id": 185,
            "label": "CONST"
        },
        {
            "id": 186,
            "label": "INIT"
        },
        {
            "id": 187,
            "label": "LT"
        },
        {
            "id": 188,
            "label": "LT"
        },
        {
            "id": 189,
            "label": "CONST"
        },
        {
            "id": 190,
            "label": "CONST"
        },
        {
            "id": 191,
            "label": "INIT"
        },
        {
            "id": 192,
            "label": "CONST"
        },
        {
            "id": 193,
            "label": "CONST"
        },
        {
            "id": 194,
            "label": "CONST"
        },
        {
            "id": 195,
            "label": "READ"
        },
        {
            "id": 196,
            "label": "READ"
        },
        {
            "id": 197,
            "label": "ADD"
        },
        {
            "id": 198,
            "label": "ADD"
        },
        {
            "id": 199,
            "label": "SUB"
        },
        {
            "id": 200,
            "label": "SUB"
        },
        {
            "id": 201,
            "label": "MUL"
        },
        {
            "id": 202,
            "label": "MUL"
        },
        {
            "id": 203,
            "label": "DIV"
        },
        {
            "id": 204,
            "label": "DIV"
        },
        {
            "id": 205,
            "label": "GT"
        },
        {
            "id": 206,
            "label": "GT"
        },
        {
            "id": 207,
            "label": "LT"
        },
        {
            "id": 208,
            "label": "LT"
        },
        {
            "id": 209,
            "label": "EQ"
        },
        {
            "id": 210,
            "label": "EQ"
        },
        {
            "id": 211,
            "label": "CONST"
        },
        {
            "id": 212,
            "label": "CONST"
        },
        {
            "id": 213,
            "label": "WRITE"
        },
        {
            "id": 214,
            "label": "WRITE"
        },
        {
            "id": 215,
            "label": "AVG_N"
        },
        {
            "id": 216,
            "label": "AVG_N"
        },
        {
            "id": 217,
            "label": "INIT"
        },
        {
            "id": 218,
            "label": "INIT"
        },
        {
            "id": 219,
            "label": "ASSIGN"
        },
        {
            "id": 220,
            "label": "ASSIGN"
        },
        {
            "id": 221,
            "label": "LT"
        },
        {
            "id": 222,
            "label": "CONST"
        },
        {
            "id": 223,
            "label": "LT"
        },
        {
            "id": 224,
            "label": "LT"
        },
        {
            "id": 225,
            "label": "ADD"
        },
        {
            "id": 226,
            "label": "LT"
        },
        {
            "id": 227,
            "label": "LT"
        },
        {
            "id": 228,
            "label": "LT"
        },
        {
            "id": 229,
            "label": "ADD"
        },
        {
            "id": 230,
            "label": "LT"
        },
        {
            "id": 231,
            "label": "LT"
        },
        {
            "id": 232,
            "label": "ADD"
        },
        {
            "id": 233,
            "label": "LT"
        },
        {
            "id": 234,
            "label": "LT"
        },
        {
            "id": 235,
            "label": "CONST"
        },
        {
            "id": 236,
            "label": "LT"
        },
        {
            "id": 237,
            "label": "LT"
        },
        {
            "id": 238,
            "label": "INIT"
        },
        {
            "id": 239,
            "label": "LT"
        },
        {
            "id": 240,
            "label": "CONST"
        },
        {
            "id": 241,
            "label": "INIT"
        },
        {
            "id": 242,
            "label": "LT"
        },
        {
            "id": 243,
            "label": "LT"
        },
        {
            "id": 244,
            "label": "CONST"
        },
        {
            "id": 245,
            "label": "INIT"
        },
        {
            "id": 246,
            "label": "INIT"
        },
        {
            "id": 247,
            "label": "LT"
        },
        {
            "id": 248,
            "label": "INIT"
        },
        {
            "id": 249,
            "label": "CONST"
        },
        {
            "id": 250,
            "label": "INIT"
        },
        {
            "id": 251,
            "label": "LT"
        },
        {
            "id": 252,
            "label": "WRITE"
        },
        {
            "id": 253,
            "label": "INIT"
        },
        {
            "id": 254,
            "label": "INIT"
        },
        {
            "id": 255,
            "label": "CONST"
        },
        {
            "id": 256,
            "label": "LT"
        },
        {
            "id": 257,
            "label": "LT"
        },
        {
            "id": 258,
            "label": "LT"
        },
        {
            "id": 259,
            "label": "INIT"
        },
        {
            "id": 260,
            "label": "LT"
        },
        {
            "id": 261,
            "label": "LT"
        },
        {
            "id": 262,
            "label": "LT"
        },
        {
            "id": 263,
            "label": "LT"
        },
        {
            "id": 264,
            "label": "LT"
        },
        {
            "id": 265,
            "label": "LT"
        },
        {
            "id": 266,
            "label": "LT"
        },
        {
            "id": 267,
            "label": "LT"
        },
        {
            "id": 268,
            "label": "LT"
        },
        {
            "id": 269,
            "label": "LT"
        },
        {
            "id": 270,
            "label": "INIT"
        },
        {
            "id": 271,
            "label": "LT"
        },
        {
            "id": 272,
            "label": "INIT"
        },
        {
            "id": 273,
            "label": "LT"
        },
        {
            "id": 274,
            "label": "LT"
        },
        {
            "id": 275,
            "label": "LT"
        },
        {
            "id": 276,
            "label": "ASSIGN"
        },
        {
            "id": 277,
            "label": "ASSIGN"
        },
        {
            "id": 278,
            "label": "ASSIGN"
        },
        {
            "id": 279,
            "label": "ASSIGN"
        },
        {
            "id": 280,
            "label": "ASSIGN"
        },
        {
            "id": 281,
            "label": "ADD"
        },
        {
            "id": 282,
            "label": "LT"
        },
        {
            "id": 283,
            "label": "LT"
        },
        {
            "id": 284,
            "label": "INIT"
        },
        {
            "id": 285,
            "label": "ADD"
        },
        {
            "id": 286,
            "label": "LT"
        },
        {
            "id": 287,
            "label": "INIT"
        },
        {
            "id": 288,
            "label": "INIT"
        },
        {
            "id": 289,
            "label": "ADD"
        },
        {
            "id": 290,
            "label": "LT"
        },
        {
            "id": 291,
            "label": "LT"
        },
        {
            "id": 292,
            "label": "CONST"
        },
        {
            "id": 293,
            "label": "LT"
        },
        {
            "id": 294,
            "label": "LT"
        },
        {
            "id": 295,
            "label": "INIT"
        },
        {
            "id": 296,
            "label": "LT"
        },
        {
            "id": 297,
            "label": "LT"
        },
        {
            "id": 298,
            "label": "INIT"
        },
        {
            "id": 299,
            "label": "LT"
        },
        {
            "id": 300,
            "label": "LT"
        },
        {
            "id": 301,
            "label": "DIV"
        },
        {
            "id": 302,
            "label": "LT"
        },
        {
            "id": 303,
            "label": "LT"
        },
        {
            "id": 304,
            "label": "WRITE"
        },
        {
            "id": 305,
            "label": "READ"
        },
        {
            "id": 306,
            "label": "READ"
        },
        {
            "id": 307,
            "label": "READ"
        },
        {
            "id": 308,
            "label": "AVG_N"
        },
        {
            "id": 309,
            "label": "CONST"
        },
        {
            "id": 310,
            "label": "LT"
        },
        {
            "id": 311,
            "label": "LT"
        },
        {
            "id": 312,
            "label": "LT"
        },
        {
            "id": 313,
            "label": "CONST"
        },
        {
            "id": 314,
            "label": "ADD"
        },
        {
            "id": 315,
            "label": "ADD"
        },
        {
            "id": 316,
            "label": "CONST"
        },
        {
            "id": 317,
            "label": "SUB"
        },
        {
            "id": 318,
            "label": "SUB"
        },
        {
            "id": 319,
            "label": "CONST"
        },
        {
            "id": 320,
            "label": "MUL"
        },
        {
            "id": 321,
            "label": "MUL"
        },
        {
            "id": 322,
            "label": "CONST"
        },
        {
            "id": 323,
            "label": "DIV"
        },
        {
            "id": 324,
            "label": "DIV"
        },
        {
            "id": 325,
            "label": "CONST"
        },
        {
            "id": 326,
            "label": "GT"
        },
        {
            "id": 327,
            "label": "LT"
        },
        {
            "id": 328,
            "label": "GT"
        },
        {
            "id": 329,
            "label": "LT"
        },
        {
            "id": 330,
            "label": "CONST"
        },
        {
            "id": 331,
            "label": "GT"
        },
        {
            "id": 332,
            "label": "GT"
        },
        {
            "id": 333,
            "label": "CONST"
        },
        {
            "id": 334,
            "label": "LT"
        },
        {
            "id": 335,
            "label": "LT"
        },
        {
            "id": 336,
            "label": "CONST"
        },
        {
            "id": 337,
            "label": "EQ"
        },
        {
            "id": 338,
            "label": "EQ"
        },
        {
            "id": 339,
            "label": "CONST"
        },
        {
            "id": 340,
            "label": "CONST"
        },
        {
            "id": 341,
            "label": "CONST"
        },
        {
            "id": 342,
            "label": "CONST"
        },
        {
            "id": 343,
            "label": "CONST"
        },
        {
            "id": 344,
            "label": "CONST"
        },
        {
            "id": 345,
            "label": "WRITE"
        },
        {
            "id": 346,
            "label": "WRITE"
        },
        {
            "id": 347,
            "label": "WRITE"
        },
        {
            "id": 348,
            "label": "CONST"
        },
        {
            "id": 349,
            "label": "LT"
        },
        {
            "id": 350,
            "label": "DIV"
        },
        {
            "id": 351,
            "label": "INIT"
        },
        {
            "id": 352,
            "label": "EQ"
        },
        {
            "id": 353,
            "label": "INIT"
        },
        {
            "id": 354,
            "label": "LT"
        },
        {
            "id": 355,
            "label": "LT"
        },
        {
            "id": 356,
            "label": "CONST"
        },
        {
            "id": 357,
            "label": "INIT"
        },
        {
            "id": 358,
            "label": "LT"
        },
        {
            "id": 359,
            "label": "INIT"
        },
        {
            "id": 360,
            "label": "INIT"
        },
        {
            "id": 361,
            "label": "EQ"
        },
        {
            "id": 362,
            "label": "CONST"
        },
        {
            "id": 363,
            "label": "EQ"
        },
        {
            "id": 364,
            "label": "LT"
        },
        {
            "id": 365,
            "label": "LT"
        },
        {
            "id": 366,
            "label": "EQ"
        },
        {
            "id": 367,
            "label": "LT"
        },
        {
            "id": 368,
            "label": "LT"
        },
        {
            "id": 369,
            "label": "EQ"
        },
        {
            "id": 370,
            "label": "READ"
        },
        {
            "id": 371,
            "label": "READ"
        },
        {
            "id": 372,
            "label": "CONST"
        },
        {
            "id": 373,
            "label": "INIT"
        },
        {
            "id": 374,
            "label": "READ"
        },
        {
            "id": 375,
            "label": "LT"
        },
        {
            "id": 376,
            "label": "LT"
        },
        {
            "id": 377,
            "label": "MUL"
        },
        {
            "id": 378,
            "label": "INIT"
        },
        {
            "id": 379,
            "label": "MUL"
        },
        {
            "id": 380,
            "label": "EQ"
        },
        {
            "id": 381,
            "label": "CONST"
        },
        {
            "id": 382,
            "label": "READ"
        },
        {
            "id": 383,
            "label": "CONST"
        },
        {
            "id": 384,
            "label": "INIT"
        },
        {
            "id": 385,
            "label": "INIT"
        },
        {
            "id": 386,
            "label": "ASSIGN"
        },
        {
            "id": 387,
            "label": "ASSIGN"
        },
        {
            "id": 388,
            "label": "INIT"
        },
        {
            "id": 389,
            "label": "INIT"
        },
        {
            "id": 390,
            "label": "READ"
        },
        {
            "id": 391,
            "label": "ASSIGN"
        },
        {
            "id": 392,
            "label": "WRITE"
        },
        {
            "id": 393,
            "label": "ADD"
        },
        {
            "id": 394,
            "label": "SUB"
        },
        {
            "id": 395,
            "label": "MUL"
        },
        {
            "id": 396,
            "label": "DIV"
        },
        {
            "id": 397,
            "label": "GT"
        },
        {
            "id": 398,
            "label": "LT"
        },
        {
            "id": 399,
            "label": "EQ"
        },
        {
            "id": 400,
            "label": "CONST"
        },
        {
            "id": 401,
            "label": "CONST"
        },
        {
            "id": 402,
            "label": "MUL"
        },
        {
            "id": 403,
            "label": "INIT"
        },
        {
            "id": 404,
            "label": "INIT"
        },
        {
            "id": 405,
            "label": "INIT"
        },
        {
            "id": 406,
            "label": "INIT"
        },
        {
            "id": 407,
            "label": "LT"
        },
        {
            "id": 408,
            "label": "INIT"
        },
        {
            "id": 409,
            "label": "INIT"
        },
        {
            "id": 410,
            "label": "CONST"
        },
        {
            "id": 411,
            "label": "LT"
        },
        {
            "id": 412,
            "label": "CONST"
        },
        {
            "id": 413,
            "label": "CONST"
        },
        {
            "id": 414,
            "label": "INIT"
        },
        {
            "id": 415,
            "label": "INIT"
        },
        {
            "id": 416,
            "label": "INIT"
        },
        {
            "id": 417,
            "label": "INIT"
        },
        {
            "id": 418,
            "label": "MUL"
        },
        {
            "id": 419,
            "label": "ADD"
        },
        {
            "id": 420,
            "label": "READ"
        },
        {
            "id": 421,
            "label": "READ"
        },
        {
            "id": 422,
            "label": "CONST"
        },
        {
            "id": 423,
            "label": "CONST"
        },
        {
            "id": 424,
            "label": "READ"
        },
        {
            "id": 425,
            "label": "READ"
        },
        {
            "id": 426,
            "label": "ADD"
        },
        {
            "id": 427,
            "label": "ADD"
        },
        {
            "id": 428,
            "label": "CONST"
        },
        {
            "id": 429,
            "label": "GT"
        },
        {
            "id": 430,
            "label": "GT"
        },
        {
            "id": 431,
            "label": "WRITE"
        },
        {
            "id": 432,
            "label": "WRITE"
        },
        {
            "id": 433,
            "label": "READ"
        },
        {
            "id": 434,
            "label": "CONST"
        },
        {
            "id": 435,
            "label": "GT"
        },
        {
            "id": 436,
            "label": "ADD"
        },
        {
            "id": 437,
            "label": "WRITE"
        },
        {
            "id": 438,
            "label": "READ"
        },
        {
            "id": 439,
            "label": "INIT"
        },
        {
            "id": 440,
            "label": "ASSIGN"
        },
        {
            "id": 441,
            "label": "LT"
        },
        {
            "id": 442,
            "label": "ASSIGN"
        },
        {
            "id": 443,
            "label": "INIT"
        },
        {
            "id": 444,
            "label": "ASSIGN"
        },
        {
            "id": 445,
            "label": "INIT"
        },
        {
            "id": 446,
            "label": "ASSIGN"
        },
        {
            "id": 447,
            "label": "LT"
        },
        {
            "id": 448,
            "label": "LT"
        },
        {
            "id": 449,
            "label": "LT"
        },
        {
            "id": 450,
            "label": "LT"
        },
        {
            "id": 451,
            "label": "ADD"
        },
        {
            "id": 452,
            "label": "INIT"
        },
        {
            "id": 453,
            "label": "ADD"
        },
        {
            "id": 454,
            "label": "ASSIGN"
        },
        {
            "id": 455,
            "label": "SUB"
        },
        {
            "id": 456,
            "label": "CONST"
        },
        {
            "id": 457,
            "label": "INIT"
        },
        {
            "id": 458,
            "label": "INIT"
        },
        {
            "id": 459,
            "label": "ASSIGN"
        },
        {
            "id": 460,
            "label": "ASSIGN"
        },
        {
            "id": 461,
            "label": "READ"
        },
        {
            "id": 462,
            "label": "READ"
        },
        {
            "id": 463,
            "label": "ASSIGN"
        },
        {
            "id": 464,
            "label": "ASSIGN"
        },
        {
            "id": 465,
            "label": "INIT"
        },
        {
            "id": 466,
            "label": "INIT"
        },
        {
            "id": 467,
            "label": "ASSIGN"
        },
        {
            "id": 468,
            "label": "ASSIGN"
        },
        {
            "id": 469,
            "label": "ADD"
        },
        {
            "id": 470,
            "label": "ADD"
        },
        {
            "id": 471,
            "label": "ASSIGN"
        },
        {
            "id": 472,
            "label": "ADD"
        },
        {
            "id": 473,
            "label": "ASSIGN"
        },
        {
            "id": 474,
            "label": "CONST"
        },
        {
            "id": 475,
            "label": "AVG_N"
        },
        {
            "id": 476,
            "label": "GT"
        },
        {
            "id": 477,
            "label": "WRITE"
        },
        {
            "id": 478,
            "label": "INIT"
        },
        {
            "id": 479,
            "label": "INIT"
        },
        {
            "id": 480,
            "label": "INIT"
        },
        {
            "id": 481,
            "label": "CONST"
        },
        {
            "id": 482,
            "label": "GT"
        },
        {
            "id": 483,
            "label": "WRITE"
        },
        {
            "id": 484,
            "label": "READ"
        },
        {
            "id": 485,
            "label": "LT"
        },
        {
            "id": 486,
            "label": "LT"
        },
        {
            "id": 487,
            "label": "LT"
        },
        {
            "id": 488,
            "label": "CONST"
        },
        {
            "id": 489,
            "label": "WRITE"
        },
        {
            "id": 490,
            "label": "INIT"
        },
        {
            "id": 491,
            "label": "LT"
        },
        {
            "id": 492,
            "label": "LT"
        },
        {
            "id": 493,
            "label": "LT"
        },
        {
            "id": 494,
            "label": "LT"
        },
        {
            "id": 495,
            "label": "LT"
        },
        {
            "id": 496,
            "label": "SUB"
        },
        {
            "id": 497,
            "label": "COROUTINE_DELAY"
        },
        {
            "id": 498,
            "label": "GT"
        },
        {
            "id": 499,
            "label": "INIT"
        },
        {
            "id": 500,
            "label": "INIT"
        },
        {
            "id": 501,
            "label": "INIT"
        },
        {
            "id": 502,
            "label": "INIT"
        },
        {
            "id": 503,
            "label": "INIT"
        },
        {
            "id": 504,
            "label": "INIT"
        },
        {
            "id": 505,
            "label": "INIT"
        },
        {
            "id": 506,
            "label": "INIT"
        },
        {
            "id": 507,
            "label": "MUL"
        },
        {
            "id": 508,
            "label": "LT"
        },
        {
            "id": 509,
            "label": "COROUTINE_YIELD"
        },
        {
            "id": 510,
            "label": "COROUTINE_DELAY"
        },
        {
            "id": 511,
            "label": "DIV"
        },
        {
            "id": 512,
            "label": "ASSIGN"
        },
        {
            "id": 513,
            "label": "ADD"
        },
        {
            "id": 514,
            "label": "GT"
        },
        {
            "id": 515,
            "label": "WRITE"
        },
        {
            "id": 516,
            "label": "LT"
        },
        {
            "id": 517,
            "label": "INIT"
        },
        {
            "id": 518,
            "label": "LT"
        },
        {
            "id": 519,
            "label": "LT"
        },
        {
            "id": 520,
            "label": "COROUTINE_YIELD"
        },
        {
            "id": 521,
            "label": "GT"
        },
        {
            "id": 522,
            "label": "COROUTINE_DELAY"
        },
        {
            "id": 523,
            "label": "INIT"
        },
        {
            "id": 524,
            "label": "EQ"
        },
        {
            "id": 525,
            "label": "CONST"
        },
        {
            "id": 526,
            "label": "GT"
        },
        {
            "id": 527,
            "label": "WRITE"
        },
        {
            "id": 528,
            "label": "READ"
        },
        {
            "id": 529,
            "label": "COROUTINE_YIELD"
        },
        {
            "id": 530,
            "label": "COROUTINE_DELAY"
        },
        {
            "id": 531,
            "label": "INIT"
        },
        {
            "id": 532,
            "label": "COROUTINE_YIELD"
        },
        {
            "id": 533,
            "label": "INIT"
        },
        {
            "id": 534,
            "label": "INIT"
        },
        {
            "id": 535,
            "label": "INIT"
        },
        {
            "id": 536,
            "label": "INIT"
        },
        {
            "id": 537,
            "label": "LT"
        },
        {
            "id": 538,
            "label": "ADD"
        },
        {
            "id": 539,
            "label": "INIT"
        },
        {
            "id": 540,
            "label": "GT"
        },
        {
            "id": 541,
            "label": "READ"
        },
        {
            "id": 542,
            "label": "READ"
        },
        {
            "id": 543,
            "label": "INIT"
        }
    ],
    "edges": [
        [
            "LT",
            "LT"
        ],
        [
            "LT",
            "ADD"
        ],
        [
            "ADD",
            "LT"
        ],
        [
            "LT",
            "READ"
        ],
        [
            "READ",
            "ADD"
        ],
        [
            "LT",
            "EQ"
        ],
        [
            "EQ",
            "INIT"
        ],
        [
            "INIT",
            "INIT"
        ],
        [
            "INIT",
            "MUL"
        ],
        [
            "MUL",
            "INIT"
        ],
        [
            "INIT",
            "LT"
        ],
        [
            "LT",
            "DIV"
        ],
        [
            "DIV",
            "INIT"
        ],
        [
            "LT",
            "INIT"
        ],
        [
            "INIT",
            "READ"
        ],
        [
            "READ",
            "READ"
        ],
        [
            "ADD",
            "MUL"
        ],
        [
            "MUL",
            "READ"
        ],
        [
            "READ",
            "LT"
        ],
        [
            "LT",
            "WRITE"
        ],
        [
            "WRITE",
            "LT"
        ],
        [
            "LT",
            "MUL"
        ],
        [
            "MUL",
            "LT"
        ],
        [
            "READ",
            "WRITE"
        ],
        [
            "WRITE",
            "ADD"
        ],
        [
            "ADD",
            "SUB"
        ],
        [
            "SUB",
            "MUL"
        ],
        [
            "MUL",
            "DIV"
        ],
        [
            "DIV",
            "CONST"
        ],
        [
            "CONST",
            "GT"
        ],
        [
            "GT",
            "LT"
        ],
        [
            "EQ",
            "ASSIGN"
        ],
        [
            "ASSIGN",
            "READ"
        ],
        [
            "READ",
            "CONST"
        ],
        [
            "CONST",
            "LT"
        ],
        [
            "MUL",
            "MUL"
        ],
        [
            "DIV",
            "LT"
        ],
        [
            "LT",
            "ASSIGN"
        ],
        [
            "ASSIGN",
            "ASSIGN"
        ],
        [
            "DIV",
            "GT"
        ],
        [
            "EQ",
            "CONST"
        ],
        [
            "CONST",
            "WRITE"
        ],
        [
            "WRITE",
            "AVG_N"
        ],
        [
            "AVG_N",
            "INIT"
        ],
        [
            "INIT",
            "ASSIGN"
        ],
        [
            "ASSIGN",
            "LT"
        ],
        [
            "READ",
            "AVG_N"
        ],
        [
            "AVG_N",
            "ADD"
        ],
        [
            "INIT",
            "DIV"
        ],
        [
            "WRITE",
            "ASSIGN"
        ],
        [
            "ASSIGN",
            "INIT"
        ],
        [
            "INIT",
            "CONST"
        ],
        [
            "CONST",
            "INIT"
        ],
        [
            "CONST",
            "READ"
        ],
        [
            "CONST",
            "ADD"
        ],
        [
            "ADD",
            "CONST"
        ],
        [
            "CONST",
            "SUB"
        ],
        [
            "SUB",
            "CONST"
        ],
        [
            "CONST",
            "MUL"
        ],
        [
            "MUL",
            "CONST"
        ],
        [
            "CONST",
            "DIV"
        ],
        [
            "GT",
            "CONST"
        ],
        [
            "LT",
            "CONST"
        ],
        [
            "CONST",
            "EQ"
        ],
        [
            "CONST",
            "CONST"
        ],
        [
            "ASSIGN",
            "CONST"
        ],
        [
            "EQ",
            "ADD"
        ],
        [
            "READ",
            "INIT"
        ],
        [
            "CONST",
            "ASSIGN"
        ],
        [
            "WRITE",
            "CONST"
        ],
        [
            "ADD",
            "ADD"
        ],
        [
            "SUB",
            "SUB"
        ],
        [
            "DIV",
            "DIV"
        ],
        [
            "GT",
            "GT"
        ],
        [
            "EQ",
            "EQ"
        ],
        [
            "WRITE",
            "WRITE"
        ],
        [
            "AVG_N",
            "AVG_N"
        ],
        [
            "WRITE",
            "INIT"
        ],
        [
            "ASSIGN",
            "ADD"
        ],
        [
            "INIT",
            "ADD"
        ],
        [
            "WRITE",
            "READ"
        ],
        [
            "AVG_N",
            "CONST"
        ],
        [
            "LT",
            "GT"
        ],
        [
            "INIT",
            "EQ"
        ],
        [
            "EQ",
            "LT"
        ],
        [
            "EQ",
            "READ"
        ],
        [
            "MUL",
            "EQ"
        ],
        [
            "READ",
            "ASSIGN"
        ],
        [
            "ASSIGN",
            "WRITE"
        ],
        [
            "MUL",
            "ADD"
        ],
        [
            "ADD",
            "READ"
        ],
        [
            "GT",
            "WRITE"
        ],
        [
            "GT",
            "ADD"
        ],
        [
            "ADD",
            "WRITE"
        ],
        [
            "ADD",
            "INIT"
        ],
        [
            "ADD",
            "ASSIGN"
        ],
        [
            "ASSIGN",
            "SUB"
        ],
        [
            "CONST",
            "AVG_N"
        ],
        [
            "AVG_N",
            "GT"
        ],
        [
            "LT",
            "SUB"
        ],
        [
            "SUB",
            "COROUTINE_DELAY"
        ],
        [
            "COROUTINE_DELAY",
            "GT"
        ],
        [
            "GT",
            "INIT"
        ],
        [
            "LT",
            "COROUTINE_YIELD"
        ],
        [
            "COROUTINE_YIELD",
            "COROUTINE_DELAY"
        ],
        [
            "COROUTINE_DELAY",
            "DIV"
        ],
        [
            "DIV",
            "ASSIGN"
        ],
        [
            "ADD",
            "GT"
        ],
        [
            "COROUTINE_YIELD",
            "GT"
        ],
        [
            "GT",
            "COROUTINE_DELAY"
        ],
        [
            "COROUTINE_DELAY",
            "INIT"
        ],
        [
            "READ",
            "COROUTINE_YIELD"
        ],
        [
            "INIT",
            "COROUTINE_YIELD"
        ],
        [
            "COROUTINE_YIELD",
            "INIT"
        ],
        [
            "INIT",
            "GT"
        ],
        [
            "GT",
            "READ"
        ],
        [
            "ADD",
            "EQ"
        ],
        [
            "READ",
            "MUL"
        ],
        [
            "INIT",
            "WRITE"
        ],
        [
            "WRITE",
            "SUB"
        ],
        [
            "SUB",
            "DIV"
        ],
        [
            "GT",
            "EQ"
        ],
        [
            "READ",
            "SUB"
        ],
        [
            "MUL",
            "GT"
        ],
        [
            "EQ",
            "WRITE"
        ],
        [
            "AVG_N",
            "ASSIGN"
        ],
        [
            "LT",
            "AVG_N"
        ],
        [
            "AVG_N",
            "LT"
        ],
        [
            "DIV",
            "WRITE"
        ],
        [
            "ASSIGN",
            "EQ"
        ],
        [
            "DIV",
            "EQ"
        ],
        [
            "READ",
            "GT"
        ],
        [
            "SUB",
            "INIT"
        ],
        [
            "ASSIGN",
            "AVG_N"
        ],
        [
            "AVG_N",
            "WRITE"
        ],
        [
            "LT",
            "COROUTINE_DELAY"
        ],
        [
            "SUB",
            "GT"
        ],
        [
            "MUL",
            "COROUTINE_YIELD"
        ],
        [
            "COROUTINE_YIELD",
            "DIV"
        ],
        [
            "COROUTINE_DELAY",
            "ASSIGN"
        ],
        [
            "DIV",
            "ADD"
        ],
        [
            "ASSIGN",
            "GT"
        ],
        [
            "COROUTINE_DELAY",
            "EQ"
        ],
        [
            "EQ",
            "GT"
        ],
        [
            "WRITE",
            "COROUTINE_YIELD"
        ],
        [
            "READ",
            "COROUTINE_DELAY"
        ],
        [
            "COROUTINE_DELAY",
            "COROUTINE_YIELD"
        ]
    ]
}